{
  "$comment": "Generated by scripts/build-registry.ts — do not edit by hand. Run `pnpm build:registry`.",
  "registryVersion": "1.0.0",
  "generatedAt": "2026-06-05",
  "bases": {
    "contextBase": "https://schemas.glideidentity.app/contexts/",
    "vctBase": "https://schemas.glideidentity.app/vct/"
  },
  "specs": {
    "w3cVcDataModel": "W3C VC Data Model 2.0 (Recommendation, 15 May 2025)",
    "sdJwtVc": "draft-ietf-oauth-sd-jwt-vc-16 (24 Apr 2026)",
    "sdJwt": "RFC 9901 (Nov 2025)",
    "jsonSchema": "JSON Schema Draft 2020-12"
  },
  "credentials": [
    {
      "id": "employee-id",
      "name": "Employee ID",
      "description": "Employer-issued workforce credential: employer, employee ID, role, department, and employment status.",
      "version": "1.0.0",
      "vct": "https://schemas.glideidentity.app/vct/employee-id",
      "context": "https://schemas.glideidentity.app/contexts/employee-id.jsonld",
      "specs": {
        "w3cVcDataModel": "W3C VC Data Model 2.0 (Recommendation, 15 May 2025)",
        "sdJwtVc": "draft-ietf-oauth-sd-jwt-vc-16 (24 Apr 2026)",
        "sdJwt": "RFC 9901 (Nov 2025)",
        "jsonSchema": "JSON Schema Draft 2020-12"
      },
      "paths": {
        "schema": "schemas/employee-id/schema.json",
        "jsonldContext": "schemas/employee-id/jsonld/context.jsonld",
        "jsonldExample": "schemas/employee-id/jsonld/example.json",
        "sdJwtVcMetadata": "schemas/employee-id/sd-jwt-vc/vct-metadata.json",
        "sdJwtVcExample": "schemas/employee-id/sd-jwt-vc/example.json",
        "readme": "schemas/employee-id/README.md"
      }
    },
    {
      "id": "proof-of-employment",
      "name": "Proof of Employment",
      "description": "Verifiable 'employed at' claim (current or former / alumni) without exposing salary or compensation.",
      "version": "1.0.0",
      "vct": "https://schemas.glideidentity.app/vct/proof-of-employment",
      "context": "https://schemas.glideidentity.app/contexts/proof-of-employment.jsonld",
      "specs": {
        "w3cVcDataModel": "W3C VC Data Model 2.0 (Recommendation, 15 May 2025)",
        "sdJwtVc": "draft-ietf-oauth-sd-jwt-vc-16 (24 Apr 2026)",
        "sdJwt": "RFC 9901 (Nov 2025)",
        "jsonSchema": "JSON Schema Draft 2020-12"
      },
      "paths": {
        "schema": "schemas/proof-of-employment/schema.json",
        "jsonldContext": "schemas/proof-of-employment/jsonld/context.jsonld",
        "jsonldExample": "schemas/proof-of-employment/jsonld/example.json",
        "sdJwtVcMetadata": "schemas/proof-of-employment/sd-jwt-vc/vct-metadata.json",
        "sdJwtVcExample": "schemas/proof-of-employment/sd-jwt-vc/example.json",
        "readme": "schemas/proof-of-employment/README.md"
      }
    },
    {
      "id": "bank-id",
      "name": "Bank ID",
      "description": "Bank-issued identity credential with verified KYC level and jurisdiction. Carries a national-ID linkage flag, never the national ID itself.",
      "version": "1.0.0",
      "vct": "https://schemas.glideidentity.app/vct/bank-id",
      "context": "https://schemas.glideidentity.app/contexts/bank-id.jsonld",
      "specs": {
        "w3cVcDataModel": "W3C VC Data Model 2.0 (Recommendation, 15 May 2025)",
        "sdJwtVc": "draft-ietf-oauth-sd-jwt-vc-16 (24 Apr 2026)",
        "sdJwt": "RFC 9901 (Nov 2025)",
        "jsonSchema": "JSON Schema Draft 2020-12"
      },
      "paths": {
        "schema": "schemas/bank-id/schema.json",
        "jsonldContext": "schemas/bank-id/jsonld/context.jsonld",
        "jsonldExample": "schemas/bank-id/jsonld/example.json",
        "sdJwtVcMetadata": "schemas/bank-id/sd-jwt-vc/vct-metadata.json",
        "sdJwtVcExample": "schemas/bank-id/sd-jwt-vc/example.json",
        "readme": "schemas/bank-id/README.md"
      }
    },
    {
      "id": "phone-verification",
      "name": "Phone Number Verification",
      "description": "Cryptographic proof of control over an E.164 phone number (not a live OTP).",
      "version": "1.0.0",
      "vct": "https://schemas.glideidentity.app/vct/phone-verification",
      "context": "https://schemas.glideidentity.app/contexts/phone-verification.jsonld",
      "specs": {
        "w3cVcDataModel": "W3C VC Data Model 2.0 (Recommendation, 15 May 2025)",
        "sdJwtVc": "draft-ietf-oauth-sd-jwt-vc-16 (24 Apr 2026)",
        "sdJwt": "RFC 9901 (Nov 2025)",
        "jsonSchema": "JSON Schema Draft 2020-12"
      },
      "paths": {
        "schema": "schemas/phone-verification/schema.json",
        "jsonldContext": "schemas/phone-verification/jsonld/context.jsonld",
        "jsonldExample": "schemas/phone-verification/jsonld/example.json",
        "sdJwtVcMetadata": "schemas/phone-verification/sd-jwt-vc/vct-metadata.json",
        "sdJwtVcExample": "schemas/phone-verification/sd-jwt-vc/example.json",
        "readme": "schemas/phone-verification/README.md"
      }
    },
    {
      "id": "email-verification",
      "name": "Email Verification",
      "description": "Proof of control over an email address.",
      "version": "1.0.0",
      "vct": "https://schemas.glideidentity.app/vct/email-verification",
      "context": "https://schemas.glideidentity.app/contexts/email-verification.jsonld",
      "specs": {
        "w3cVcDataModel": "W3C VC Data Model 2.0 (Recommendation, 15 May 2025)",
        "sdJwtVc": "draft-ietf-oauth-sd-jwt-vc-16 (24 Apr 2026)",
        "sdJwt": "RFC 9901 (Nov 2025)",
        "jsonSchema": "JSON Schema Draft 2020-12"
      },
      "paths": {
        "schema": "schemas/email-verification/schema.json",
        "jsonldContext": "schemas/email-verification/jsonld/context.jsonld",
        "jsonldExample": "schemas/email-verification/jsonld/example.json",
        "sdJwtVcMetadata": "schemas/email-verification/sd-jwt-vc/vct-metadata.json",
        "sdJwtVcExample": "schemas/email-verification/sd-jwt-vc/example.json",
        "readme": "schemas/email-verification/README.md"
      }
    },
    {
      "id": "age-verification",
      "name": "Age Verification",
      "description": "Proves a holder's age via boolean age-over predicates and/or a selectively disclosable birthdate. Designed so a holder can present only a predicate (e.g. age_over_18) without revealing birthdate.",
      "version": "1.0.0",
      "vct": "https://schemas.glideidentity.app/vct/age-verification",
      "context": "https://schemas.glideidentity.app/contexts/age-verification.jsonld",
      "specs": {
        "w3cVcDataModel": "W3C VC Data Model 2.0 (Recommendation, 15 May 2025)",
        "sdJwtVc": "draft-ietf-oauth-sd-jwt-vc-16 (24 Apr 2026)",
        "sdJwt": "RFC 9901 (Nov 2025)",
        "jsonSchema": "JSON Schema Draft 2020-12"
      },
      "paths": {
        "schema": "schemas/age-verification/schema.json",
        "jsonldContext": "schemas/age-verification/jsonld/context.jsonld",
        "jsonldExample": "schemas/age-verification/jsonld/example.json",
        "sdJwtVcMetadata": "schemas/age-verification/sd-jwt-vc/vct-metadata.json",
        "sdJwtVcExample": "schemas/age-verification/sd-jwt-vc/example.json",
        "readme": "schemas/age-verification/README.md"
      }
    },
    {
      "id": "education-certificate",
      "name": "Education Certificate",
      "description": "An academic credential: institution, degree, field of study, award date, optional grade, and accreditation body.",
      "version": "1.0.0",
      "vct": "https://schemas.glideidentity.app/vct/education-certificate",
      "context": "https://schemas.glideidentity.app/contexts/education-certificate.jsonld",
      "specs": {
        "w3cVcDataModel": "W3C VC Data Model 2.0 (Recommendation, 15 May 2025)",
        "sdJwtVc": "draft-ietf-oauth-sd-jwt-vc-16 (24 Apr 2026)",
        "sdJwt": "RFC 9901 (Nov 2025)",
        "jsonSchema": "JSON Schema Draft 2020-12"
      },
      "paths": {
        "schema": "schemas/education-certificate/schema.json",
        "jsonldContext": "schemas/education-certificate/jsonld/context.jsonld",
        "jsonldExample": "schemas/education-certificate/jsonld/example.json",
        "sdJwtVcMetadata": "schemas/education-certificate/sd-jwt-vc/vct-metadata.json",
        "sdJwtVcExample": "schemas/education-certificate/sd-jwt-vc/example.json",
        "readme": "schemas/education-certificate/README.md"
      }
    },
    {
      "id": "boarding-pass",
      "name": "Boarding Pass",
      "description": "A flight boarding pass: passenger, carrier, flight, route, departure, seat, boarding group, and disclosable PNR.",
      "version": "1.0.0",
      "vct": "https://schemas.glideidentity.app/vct/boarding-pass",
      "context": "https://schemas.glideidentity.app/contexts/boarding-pass.jsonld",
      "specs": {
        "w3cVcDataModel": "W3C VC Data Model 2.0 (Recommendation, 15 May 2025)",
        "sdJwtVc": "draft-ietf-oauth-sd-jwt-vc-16 (24 Apr 2026)",
        "sdJwt": "RFC 9901 (Nov 2025)",
        "jsonSchema": "JSON Schema Draft 2020-12"
      },
      "paths": {
        "schema": "schemas/boarding-pass/schema.json",
        "jsonldContext": "schemas/boarding-pass/jsonld/context.jsonld",
        "jsonldExample": "schemas/boarding-pass/jsonld/example.json",
        "sdJwtVcMetadata": "schemas/boarding-pass/sd-jwt-vc/vct-metadata.json",
        "sdJwtVcExample": "schemas/boarding-pass/sd-jwt-vc/example.json",
        "readme": "schemas/boarding-pass/README.md"
      }
    }
  ]
}
